pytest_testinel/__init__.py
pytest_testinel/results_reporter.py
pytest_testinel/testinel.py
pytest_testinel-0.2.1.dist-info/licenses/LICENSE
pytest_testinel-0.2.1.dist-info/WHEEL
pytest_testinel-0.2.1.dist-info/entry_points.txt
pytest_testinel-0.2.1.dist-info/METADATA
pytest_testinel-0.2.1.dist-info/RECORD
