Metadata-Version: 2.4
Name: pytest-testinel
Version: 0.2.1
Summary: Testinel’s pytest plugin captures structured test execution data directly from pytest and sends it to Testinel, where your test results become searchable, comparable, and actually useful.
Author: Volodymyr Obrizan
Author-email: Volodymyr Obrizan <obrizan@first.institute>
License-Expression: MIT
License-File: LICENSE
Classifier: Programming Language :: Python :: 3
Classifier: Operating System :: OS Independent
Classifier: Development Status :: 4 - Beta
Classifier: Framework :: Pytest
Classifier: Topic :: Software Development :: Testing
Requires-Dist: pytest>=7
Requires-Dist: requests>=2
Requires-Python: >=3.10
Project-URL: Homepage, https://github.com/Testinel/pytest-testinel
Project-URL: Issues, https://github.com/Testinel/pytest-testinel/issues
